SeleniumDoc/README.md
SeleniumDoc/__init__.py
SeleniumDoc/__main__.py
SeleniumDoc/file.epub
SeleniumDoc/index.html
SeleniumDoc/css/__init__.py
SeleniumDoc/css/annotations.css
SeleniumDoc/css/main.css
SeleniumDoc/css/normalize.css
SeleniumDoc/css/popup.css
SeleniumDoc/font/__init__.py
SeleniumDoc/font/fontello.eot
SeleniumDoc/font/fontello.svg
SeleniumDoc/font/fontello.ttf
SeleniumDoc/font/fontello.woff
SeleniumDoc/img/__init__.py
SeleniumDoc/img/annotator-glyph-sprite.png
SeleniumDoc/img/annotator-icon-sprite.png
SeleniumDoc/img/apple-touch-icon.png
SeleniumDoc/img/cancelfullscreen.png
SeleniumDoc/img/close.png
SeleniumDoc/img/fullscreen.png
SeleniumDoc/img/loader.gif
SeleniumDoc/img/menu-icon.png
SeleniumDoc/img/save.png
SeleniumDoc/img/saved.png
SeleniumDoc/img/settings-s.png
SeleniumDoc/img/settings.png
SeleniumDoc/img/star.png
SeleniumDoc/js/__init__.py
SeleniumDoc/js/epub.js
SeleniumDoc/js/epub.min.js
SeleniumDoc/js/epub.min.map
SeleniumDoc/js/hooks.min.js
SeleniumDoc/js/hooks.min.map
SeleniumDoc/js/reader.js
SeleniumDoc/js/reader.js.map
SeleniumDoc/js/reader.min.js
SeleniumDoc/js/reader.min.map
SeleniumDoc/js/hooks/__init__.py
SeleniumDoc/js/hooks/extensions/__init__.py
SeleniumDoc/js/hooks/extensions/highlight.js
SeleniumDoc/js/libs/__init__.py
SeleniumDoc/js/libs/jquery.min.js
SeleniumDoc/js/libs/localforage.min.js
SeleniumDoc/js/libs/screenfull.js
SeleniumDoc/js/libs/screenfull.min.js
SeleniumDoc/js/libs/zip.min.js
SeleniumDoc/js/plugins/__init__.py
SeleniumDoc/js/plugins/hypothesis.js
SeleniumDoc/js/plugins/search.js
selenium_doc-2024.3.1.0.dist-info/METADATA
selenium_doc-2024.3.1.0.dist-info/WHEEL
selenium_doc-2024.3.1.0.dist-info/entry_points.txt
selenium_doc-2024.3.1.0.dist-info/top_level.txt
selenium_doc-2024.3.1.0.dist-info/RECORD
